<annotation>
	<folder>clean_sticky_notes</folder>
	<filename>istockphoto-162714400-170667a.jpg</filename>
	<path>C:\Users\vbraz\Desktop\sticky-notes-downloaded-images\clean_sticky_notes\istockphoto-162714400-170667a.jpg</path>
	<source>
		<database>Unknown</database>
	</source>
	<size>
		<width>507</width>
		<height>338</height>
		<depth>3</depth>
	</size>
	<segmented>0</segmented>
	<object>
		<name>yellow_sticky_note</name>
		<pose>Unspecified</pose>
		<truncated>0</truncated>
		<difficult>0</difficult>
		<bndbox>
			<xmin>84</xmin>
			<ymin>31</ymin>
			<xmax>168</xmax>
			<ymax>115</ymax>
		</bndbox>
	</object>
	<object>
		<name>orange_sticky_note</name>
		<pose>Unspecified</pose>
		<truncated>0</truncated>
		<difficult>0</difficult>
		<bndbox>
			<xmin>205</xmin>
			<ymin>31</ymin>
			<xmax>290</xmax>
			<ymax>111</ymax>
		</bndbox>
	</object>
	<object>
		<name>pink_sticky_note</name>
		<pose>Unspecified</pose>
		<truncated>0</truncated>
		<difficult>0</difficult>
		<bndbox>
			<xmin>315</xmin>
			<ymin>30</ymin>
			<xmax>402</xmax>
			<ymax>111</ymax>
		</bndbox>
	</object>
	<object>
		<name>orange_sticky_note</name>
		<pose>Unspecified</pose>
		<truncated>0</truncated>
		<difficult>0</difficult>
		<bndbox>
			<xmin>85</xmin>
			<ymin>228</ymin>
			<xmax>170</xmax>
			<ymax>311</ymax>
		</bndbox>
	</object>
	<object>
		<name>pink_sticky_note</name>
		<pose>Unspecified</pose>
		<truncated>0</truncated>
		<difficult>0</difficult>
		<bndbox>
			<xmin>86</xmin>
			<ymin>125</ymin>
			<xmax>172</xmax>
			<ymax>208</ymax>
		</bndbox>
	</object>
	<object>
		<name>yellow_sticky_note</name>
		<pose>Unspecified</pose>
		<truncated>0</truncated>
		<difficult>0</difficult>
		<bndbox>
			<xmin>209</xmin>
			<ymin>127</ymin>
			<xmax>292</xmax>
			<ymax>208</ymax>
		</bndbox>
	</object>
	<object>
		<name>yellow_sticky_note</name>
		<pose>Unspecified</pose>
		<truncated>0</truncated>
		<difficult>0</difficult>
		<bndbox>
			<xmin>323</xmin>
			<ymin>225</ymin>
			<xmax>411</xmax>
			<ymax>310</ymax>
		</bndbox>
	</object>
	<object>
		<name>pink_sticky_note</name>
		<pose>Unspecified</pose>
		<truncated>0</truncated>
		<difficult>0</difficult>
		<bndbox>
			<xmin>214</xmin>
			<ymin>225</ymin>
			<xmax>298</xmax>
			<ymax>310</ymax>
		</bndbox>
	</object>
	<object>
		<name>orange_sticky_note</name>
		<pose>Unspecified</pose>
		<truncated>0</truncated>
		<difficult>0</difficult>
		<bndbox>
			<xmin>318</xmin>
			<ymin>128</ymin>
			<xmax>406</xmax>
			<ymax>210</ymax>
		</bndbox>
	</object>
</annotation>
